ml_spyking_circus/__init__.py
ml_spyking_circus/ml_spyking_circus.py.mp
ml_spyking_circus/ml_spyking_circus_run.py
ml_spyking_circus-0.1.6.dist-info/METADATA
ml_spyking_circus-0.1.6.dist-info/RECORD
ml_spyking_circus-0.1.6.dist-info/WHEEL
ml_spyking_circus-0.1.6.dist-info/top_level.txt
