Metadata-Version: 2.1
Name: ml-spyking-circus
Version: 0.1.6
Summary: MountainLab wrapper for spyking circus
Home-page: https://github.com/magland/ml_spyking_circus
Author: Jeremy Magland
Author-email: 
License: UNKNOWN
Platform: UNKNOWN
Classifier: Programming Language :: Python :: 3
Classifier: License :: OSI Approved :: Apache Software License
Classifier: Operating System :: OS Independent
Requires-Dist: numpy
Requires-Dist: mlprocessors
Requires-Dist: mountainlab-pytools
Requires-Dist: numpydoc
Requires-Dist: h5py
